Workbook

Sheet Sales_Data
A1: Date | B1: Product | C1: Category | D1: Qty | E1: Unit Price | F1: Total
A2: 2025-01-01 | B2: Cooking Oil 1L | C2: Staples | D2: 4 | E2: =VLOOKUP(B2,Price_List!A:B,2,FALSE) -> 18000 | F2: =D2*E2 -> 72000
A3: 2025-01-01 | B3: Rice 5kg | C3: Staples | D3: 9 | E3: =VLOOKUP(B3,Price_List!A:B,2,FALSE) -> 75000 | F3: =D3*E3 -> 675000
A4: 2025-01-01 | B4: Instant Noodles | C4: Food | D4: 3 | E4: =VLOOKUP(B4,Price_List!A:B,2,FALSE) -> 3500 | F4: =D4*E4 -> 10500
A5: 2025-01-01 | B5: Soap | C5: Toiletries | D5: 2 | E5: =VLOOKUP(B5,Price_List!A:B,2,FALSE) -> 5000 | F5: =D5*E5 -> 10000
A6: 2025-01-01 | B6: Instant Noodles | C6: Food | D6: 3 | E6: =VLOOKUP(B6,Price_List!A:B,2,FALSE) -> 3500 | F6: =D6*E6 -> 10500
A7: 2025-01-02 | B7: Rice 5kg | C7: Staples | D7: 4 | E7: =VLOOKUP(B7,Price_List!A:B,2,FALSE) -> 75000 | F7: =D7*E7 -> 300000
A8: 2025-01-02 | B8: Eggs 1kg | C8: Staples | D8: 9 | E8: =VLOOKUP(B8,Price_List!A:B,2,FALSE) -> 30000 | F8: =D8*E8 -> 270000
A9: 2025-01-02 | B9: Sugar 1kg | C9: Staples | D9: 5 | E9: =VLOOKUP(B9,Price_List!A:B,2,FALSE) -> 14000 | F9: =D9*E9 -> 70000
A10: 2025-01-02 | B10: Milk UHT | C10: Beverage | D10: 8 | E10: =VLOOKUP(B10,Price_List!A:B,2,FALSE) -> 7000 | F10: =D10*E10 -> 56000
A11: 2025-01-02 | B11: Cooking Oil 1L | C11: Staples | D11: 10 | E11: =VLOOKUP(B11,Price_List!A:B,2,FALSE) -> 18000 | F11: =D11*E11 -> 180000
A12: 2025-01-03 | B12: Cooking Oil 1L | C12: Staples | D12: 4 | E12: =VLOOKUP(B12,Price_List!A:B,2,FALSE) -> 18000 | F12: =D12*E12 -> 72000
A13: 2025-01-03 | B13: Rice 5kg | C13: Staples | D13: 3 | E13: =VLOOKUP(B13,Price_List!A:B,2,FALSE) -> 75000 | F13: =D13*E13 -> 225000
... A201: 2025-02-09 | B201: Tea Bags | C201: Beverage | D201: 3 | E201: =VLOOKUP(B201,Price_List!A:B,2,FALSE) -> 5000 | F201: =D201*E201 -> 15000

Sheet Price_List
A1: Product | B1: Unit Price
A2: Rice 5kg | B2: 75000
A3: Sugar 1kg | B3: 14000
A4: Cooking Oil 1L | B4: 18000
A5: Eggs 1kg | B5: 30000
A6: Instant Noodles | B6: 3500
A7: Milk UHT | B7: 7000
A8: Coffee Sachet | B8: 2000
A9: Tea Bags | B9: 5000
A10: Shampoo | B10: 25000
A11: Soap | B11: 5000

Sheet Financial_Report
A1: Description | B1: Amount
A2: Revenue | B2: =SUM(Sales_Data!F2:F201) -> 18565500
A3: Expenses | B3: 5000000
A4: Profit | B4: =B2-B3 -> 13565500
